mysense/__init__.py
mysense/json_logger.py
mysense/utils.py
mysense-0.5.1.dist-info/LICENSE
mysense-0.5.1.dist-info/METADATA
mysense-0.5.1.dist-info/WHEEL
mysense-0.5.1.dist-info/top_level.txt
mysense-0.5.1.dist-info/RECORD
