Metadata-Version: 2.1
Name: mysense
Version: 0.5.1
Summary: Helper functions
Home-page: UNKNOWN
Author: MySense Ltd.
Author-email: nikita.tarasov@mysense.ai
License: UNKNOWN
Platform: UNKNOWN
Classifier: Programming Language :: Python :: 3
Classifier: License :: OSI Approved :: MIT License
Classifier: Operating System :: OS Independent
